d3heatmap/__init__.py
d3heatmap/d3heatmap.py
d3heatmap/examples.py
d3heatmap/d3js/__init__.py
d3heatmap/d3js/d3.scale.chromatic.v1.min.js
d3heatmap/d3js/d3.v2.min.js
d3heatmap/d3js/d3.v4.js
d3heatmap/d3js/d3heatmap.html
d3heatmap/d3js/d3script.html
d3heatmap-0.2.3.dist-info/LICENSE
d3heatmap-0.2.3.dist-info/METADATA
d3heatmap-0.2.3.dist-info/WHEEL
d3heatmap-0.2.3.dist-info/top_level.txt
d3heatmap-0.2.3.dist-info/RECORD
