Metadata-Version: 2.1
Name: d3heatmap
Version: 0.2.3
Summary: Python package to create interactive heatmap based on d3js.
Home-page: https://github.com/erdogant/d3heatmap
Download-URL: https://github.com/erdogant/d3heatmap/archive/0.2.3.tar.gz
Author: Erdogan Taskesen
Author-email: erdogant@gmail.com
Classifier: Programming Language :: Python :: 3
Classifier: License :: OSI Approved :: MIT License
Classifier: Operating System :: OS Independent
Requires-Python: >=3
License-File: LICENSE
Requires-Dist: ismember
Requires-Dist: clusteval
Requires-Dist: numpy
Requires-Dist: pandas
